pytaste/__init__.py
pytaste-0.0.1.dist-info/METADATA
pytaste-0.0.1.dist-info/WHEEL
pytaste-0.0.1.dist-info/top_level.txt
pytaste-0.0.1.dist-info/RECORD
